{"gameId":193322,"name":"Master of Orion: The Board Game","description":"Master of Orion: The Board Game takes you to the world of the legendary strategy video game.&#10;&#10;You will lead one of the races that will face each other in the outer space confrontation. Destinies of secretive Darloks, genius Psilons, universal humans and many others will depend on your actions. Manage your resources skillfully and wisely and lead the development of a chosen race in the right direction. You can progress by either military means, training your spies and attacking alien planets, or choose the path of creation, controlling the weather and building space fleets.&#10;&#10;A dynamic and well-balanced game mechanics will offer you plenty of paths to the victory, and the leader of the most successful nation will be granted the Emperor's title from the Galactic Council.&#10;&#10;","image":"https://cf.geekdo-images.com/original/img/V00fYa-AQng_VXEiAtRmNSjDUHU=/0x0/pic3555039.jpg","thumbnail":"https://cf.geekdo-images.com/thumb/img/gZ8BWyzmUlV9-CeYSYo5E9mIw5s=/fit-in/200x150/filters:strip_icc()/pic3555039.jpg","minPlayers":2,"maxPlayers":4,"playingTime":60,"mechanics":["Action Points","Hand Management","Turn Order: Progressive","Variable Player Powers"],"isExpansion":false,"yearPublished":2016,"bggRating":6.10889,"averageRating":6.96573,"rank":1945,"designers":["Ekaterina Gorn","Igor Sklyuev"],"publishers":["Cryptozoic Entertainment","Grimspire","Hobby World","Last Level","MINDOK","Rebel Sp. z o.o."],"artists":[],"playerPollResults":[{"numPlayers":1,"best":0,"recommended":0,"notRecommended":18,"numPlayersIsAndHigher":false},{"numPlayers":2,"best":10,"recommended":15,"notRecommended":0,"numPlayersIsAndHigher":false},{"numPlayers":3,"best":12,"recommended":9,"notRecommended":0,"numPlayersIsAndHigher":false},{"numPlayers":4,"best":6,"recommended":13,"notRecommended":1,"numPlayersIsAndHigher":false},{"numPlayers":4,"best":0,"recommended":3,"notRecommended":10,"numPlayersIsAndHigher":true}]}